mxmftools/__init__.py
mxmftools/matplotlibrc
mxmftools/calculate/__init__.py
mxmftools/calculate/vasp.py
mxmftools/cli/__init__.py
mxmftools/cli/cli.py
mxmftools/cli/phonopy/__init__.py
mxmftools/cli/phonopy/band.py
mxmftools/cli/vasp/__init__.py
mxmftools/cli/vasp/band.py
mxmftools/cli/vasp/common.py
mxmftools/cli/vasp/dos.py
mxmftools/cli/vaspberry/__init__.py
mxmftools/cli/vaspberry/curv.py
mxmftools/cli/wannier90/__init__.py
mxmftools/cli/wannier90/band.py
mxmftools/cli/wannier90/compare.py
mxmftools/data_handle/__init__.py
mxmftools/data_handle/get_gap.py
mxmftools/data_handle/get_prolist.py
mxmftools/data_read/__init__.py
mxmftools/data_read/read_h5.py
mxmftools/data_read/read_kpoints.py
mxmftools/data_read/read_xml.py
mxmftools/figplot/__init__.py
mxmftools/figplot/phononband.py
mxmftools/figplot/vaspband.py
mxmftools/figplot/vaspberry.py
mxmftools/figplot/vaspdos.py
mxmftools/figplot/wannier90.py
mxmftools/scripts/__init__.py
mxmftools/scripts/plotfromcli.py
mxmftools/utils/__init__.py
mxmftools/utils/click_utils.py
mxmftools-0.1.1.dist-info/LICENSE
mxmftools-0.1.1.dist-info/METADATA
mxmftools-0.1.1.dist-info/WHEEL
mxmftools-0.1.1.dist-info/entry_points.txt
mxmftools-0.1.1.dist-info/top_level.txt
mxmftools-0.1.1.dist-info/RECORD
